sequence_qc/VERSION
sequence_qc/__init__.py
sequence_qc/cli.py
sequence_qc/noise.py
sequence_qc/noise_by_tlen.py
sequence_qc/plot_noise_by_tlen.py
sequence_qc/plots.py
sequence_qc-0.2.2.dist-info/AUTHORS.rst
sequence_qc-0.2.2.dist-info/LICENSE
sequence_qc-0.2.2.dist-info/METADATA
sequence_qc-0.2.2.dist-info/WHEEL
sequence_qc-0.2.2.dist-info/entry_points.txt
sequence_qc-0.2.2.dist-info/top_level.txt
sequence_qc-0.2.2.dist-info/RECORD
