Metadata-Version: 2.1
Name: sequence-qc
Version: 0.2.2
Summary: Package for doing various ad-hoc quality control steps from MSK-ACCESS generated FASTQ or BAM files
Home-page: https://github.com/msk-access/sequence_qc
Author: Ian Johnson
Author-email: ionox0@gmail.com
License: Apache Software License 2.0
Keywords: sequence_qc
Platform: UNKNOWN
Classifier: Development Status :: 2 - Pre-Alpha
Classifier: Intended Audience :: Developers
Classifier: License :: OSI Approved :: Apache Software License
Classifier: Natural Language :: English
Classifier: Programming Language :: Python :: 3
Classifier: Programming Language :: Python :: 3.5
Classifier: Programming Language :: Python :: 3.6
Classifier: Programming Language :: Python :: 3.7
Classifier: Programming Language :: Python :: 3.8
Requires-Python: >=3.5
Requires-Dist: pysam (==0.15.4)
Requires-Dist: pybedtools (==0.8.1)
Requires-Dist: pyfaidx (==0.5.8)
Requires-Dist: click (==7.1.2)
Requires-Dist: pysamstats (==1.1.2)
Requires-Dist: pandas
Requires-Dist: plotly
Requires-Dist: scipy (==1.5.0)
